__init__.py
library_design.py
core/__init__.py
core/app_gui.py
core/args.py
core/data_function.py
core/design_process.py
core/function.py
core/gui_function.py
models/__init__.py
models/interface.py
models/invalidNbrLocusException.py
models/library.py
models/locus.py
models/tooltip.py
resources/Barcodes.csv
resources/Caution.png
resources/List_RT.csv
resources/Primer_univ.csv
resources/__init__.py
resources/chr3L.bed
resources/info.png
resources/input_parameters.json
resources/tooltip_text.json
MFISH_lib_design-0.0.1.dist-info/LICENCE
MFISH_lib_design-0.0.1.dist-info/METADATA
MFISH_lib_design-0.0.1.dist-info/WHEEL
MFISH_lib_design-0.0.1.dist-info/entry_points.txt
MFISH_lib_design-0.0.1.dist-info/top_level.txt
MFISH_lib_design-0.0.1.dist-info/RECORD
