Metadata-Version: 2.1
Name: MFISH_lib_design
Version: 0.0.1
Summary: Pipeline to generate probes for multiplexed DNA-FISH
Author-email: Christophe Houbron <christof.houbron@gmail.com>
License: MIT License
Project-URL: Homepage, https://github.com/Christof-H/Library_Design_tools
Project-URL: Issues, https://github.com/Christof-H/Library_Design_tools/issues
Classifier: Programming Language :: Python :: 3
Classifier: License :: OSI Approved :: MIT License
Classifier: Operating System :: OS Independent
Requires-Python: >=3.10
License-File: LICENCE
Requires-Dist: matplotlib >=3.9.0
Provides-Extra: dev
Requires-Dist: black ; extra == 'dev'
Requires-Dist: pytest ; extra == 'dev'
